phantom_eval/__init__.py
phantom_eval/__main__.py
phantom_eval/_types.py
phantom_eval/constants.py
phantom_eval/evaluate_utils.py
phantom_eval/gpu_utils.py
phantom_eval/plotting_utils.py
phantom_eval/prolog_utils.py
phantom_eval/prompts.py
phantom_eval/score.py
phantom_eval/utils.py
phantom_eval/agents/__init__.py
phantom_eval/agents/common.py
phantom_eval/agents/cot.py
phantom_eval/agents/manager.py
phantom_eval/agents/nshot.py
phantom_eval/agents/react.py
phantom_eval/llm/__init__.py
phantom_eval/llm/anthropic.py
phantom_eval/llm/common.py
phantom_eval/llm/gemini.py
phantom_eval/llm/llama.py
phantom_eval/llm/llms_rpm_tpm_config.yaml
phantom_eval/llm/openai.py
phantom_eval/llm/together.py
phantom_eval/llm/vllm.py
phantom_wiki/__init__.py
phantom_wiki/__main__.py
phantom_wiki/generate_dataset.py
phantom_wiki/core/__init__.py
phantom_wiki/core/article.py
phantom_wiki/core/questions.py
phantom_wiki/core/constants/__init__.py
phantom_wiki/core/constants/article_templates.py
phantom_wiki/core/constants/relation_templates.py
phantom_wiki/facts/__init__.py
phantom_wiki/facts/database.py
phantom_wiki/facts/question_difficulty.py
phantom_wiki/facts/sample.py
phantom_wiki/facts/templates.py
phantom_wiki/facts/attributes/__init__.py
phantom_wiki/facts/attributes/constants.py
phantom_wiki/facts/attributes/generate_attributes.py
phantom_wiki/facts/attributes/rules.pl
phantom_wiki/facts/family/__init__.py
phantom_wiki/facts/family/constants.py
phantom_wiki/facts/family/generate.py
phantom_wiki/facts/family/person_factory.py
phantom_wiki/facts/family/rules_base.pl
phantom_wiki/facts/family/rules_derived.pl
phantom_wiki/facts/family/names/female_names.json
phantom_wiki/facts/family/names/last_names.json
phantom_wiki/facts/family/names/male_names.json
phantom_wiki/facts/friends/__init__.py
phantom_wiki/facts/friends/constants.py
phantom_wiki/facts/friends/generate.py
phantom_wiki/facts/friends/rules.pl
phantom_wiki/utils/__init__.py
phantom_wiki/utils/family.py
phantom_wiki-1.0.2.dist-info/licenses/LICENSE
phantom_wiki-1.0.2.dist-info/METADATA
phantom_wiki-1.0.2.dist-info/WHEEL
phantom_wiki-1.0.2.dist-info/entry_points.txt
phantom_wiki-1.0.2.dist-info/top_level.txt
phantom_wiki-1.0.2.dist-info/RECORD
