Metadata-Version: 2.4
Name: phantom-wiki
Version: 1.0.2
Summary: On-Demand Datasets for Reasoning and Retrieval Evaluation
Author-email: Albert Gong <ag2435@cornell.edu>, Chao Wan <cw862@cornell.edu>, Kamilė Stankevičiūtė <ks2448@cornell.edu>, Anmol Kabra <anmol@cs.cornell.edu>, Raphael Thesmar <rft38@cornell.edu>, Johann Lee <jcl354@cornell.edu>, JT Klenke <jtk96@cornell.edu>, Carla Gomes <gomes@cs.cornell.edu>, Kilian Weinberger <kilian@cornell.edu>
Project-URL: Homepage, https://github.com/kilian-group/phantom-wiki
Project-URL: Issues, https://github.com/kilian-group/phantom-wiki/issues
Project-URL: Repository, https://github.com/kilian-group/phantom-wiki.git
Classifier: Programming Language :: Python :: 3
Classifier: License :: OSI Approved :: MIT License
Classifier: Operating System :: OS Independent
Requires-Python: >=3.12
License-File: LICENSE
Requires-Dist: matplotlib>=3.10.0
Requires-Dist: networkx
Requires-Dist: nltk>=3.9.1
Requires-Dist: numpy>=1.26.4
Requires-Dist: pandas>=2.2.2
Requires-Dist: pydot>=1.4.2
Requires-Dist: pyswip>=0.3.2
Requires-Dist: tabulate
Requires-Dist: termcolor
Requires-Dist: tqdm
Provides-Extra: dev
Requires-Dist: pre-commit; extra == "dev"
Requires-Dist: black; extra == "dev"
Provides-Extra: tests
Requires-Dist: pytest; extra == "tests"
Requires-Dist: pytest-cov; extra == "tests"
Requires-Dist: rootutils; extra == "tests"
Provides-Extra: docs
Requires-Dist: mkdocs==1.6.0; extra == "docs"
Requires-Dist: mkdocs-material==9.5.31; extra == "docs"
Requires-Dist: mkdocstrings[python,shell]==0.25.2; extra == "docs"
Requires-Dist: mkdocs-gen-files==0.5.0; extra == "docs"
Requires-Dist: mkdocs-literate-nav==0.6.1; extra == "docs"
Requires-Dist: mkdocs-section-index==0.3.9; extra == "docs"
Requires-Dist: mkdocs-git-authors-plugin==0.9.0; extra == "docs"
Requires-Dist: mkdocs-git-revision-date-localized-plugin==1.2.6; extra == "docs"
Provides-Extra: eval
Requires-Dist: anthropic; extra == "eval"
Requires-Dist: datasets>=3.1.0; extra == "eval"
Requires-Dist: faiss-cpu>=1.9.0.post1; extra == "eval"
Requires-Dist: google-generativeai; extra == "eval"
Requires-Dist: langchain>=0.3.14; extra == "eval"
Requires-Dist: langchain-community; extra == "eval"
Requires-Dist: langchain-together; extra == "eval"
Requires-Dist: openai; extra == "eval"
Requires-Dist: scipy; extra == "eval"
Requires-Dist: tiktoken; extra == "eval"
Requires-Dist: together; extra == "eval"
Requires-Dist: transformers>=4.51.0; extra == "eval"
Requires-Dist: bm25s[full]; extra == "eval"
Requires-Dist: vllm>=0.8.5; extra == "eval"
Requires-Dist: flashrag-dev; extra == "eval"
Dynamic: license-file
